{
    "Anora": [
        {
            "source": {
                "id": null,
                "name": "/FILM"
            },
            "author": "staff@slashfilm.com (BJ Colangelo)",
            "title": "The Best Movie Of 2024 Teaches Hollywood A Lesson It's Been Ignoring For Years",
            "description": "Sean Baker, the writer/director of Anora, has some advice for Hollywood about how to create authentic representation for marginalized groups on screen.",
            "url": "https://www.slashfilm.com/1684647/best-movie-2024-teaches-hollywood-lesson-sean-baker-anora-representation/",
            "urlToImage": "https://www.slashfilm.com/img/gallery/the-best-movie-of-2024-teaches-hollywood-a-lesson-its-been-ignoring-for-years/l-intro-1728510639.jpg",
            "publishedAt": "2024-11-15T19:00:00Z",
            "content": "There's a moment in \"The Florida Project,\" the Willem Dafoe-starring drama from Sean Baker about a six-year-old girl named Moonee (Brooklynn Prince) living in a motel with her mother Halley (Bria Vin\u2026 [+1987 chars]"
        },
        {
            "source": {
                "id": null,
                "name": "Deadline"
            },
            "author": "Denise Petski",
            "title": "Nude Audition Landed Mark Eydelshteyn Role Of Mikey Madison\u2019s \u2018Anora\u2019 Love Interest \u2013 Contenders Los Angeles",
            "description": "Writer/director Sean Baker does his own casting so he was reviewing many contenders for the role of Ivan, son of a Russian oligarch in Anora. Mark Eydelshteyn impressed Baker by sending him a self-tape where he performed all of his lines in the nude. \u201cIt\u2019s ve\u2026",
            "url": "http://deadline.com/2024/11/anora-mikey-madison-mark-eydelshteyn-sean-baker-interview-1236178881/",
            "urlToImage": "https://deadline.com/wp-content/uploads/2024/11/Anora-contenders.jpg?w=1024",
            "publishedAt": "2024-11-16T18:59:59Z",
            "content": "Writer/director Sean Baker does his own casting so he was reviewing many contenders for the role of Ivan, son of a Russian oligarch in Anora. Mark Eydelshteyn impressed Baker by sending him a self-ta\u2026 [+3347 chars]"
        },
        {
            "source": {
                "id": null,
                "name": "HYPEBEAST"
            },
            "author": "info@hypebeast.com (Hypebeast)",
            "title": "Conan O'Brien To Host 2025 Oscars",
            "description": "The Academy of Motion Picture Arts and Sciences has named Conan O'Brien as the host of the 97th Academy Awards.The comedian, host and writer is set to take over hosting duties from Jimmy Kimmel, who served as the Oscars host for two years straight. \u201cAmerica d\u2026",
            "url": "https://hypebeast.com/2024/11/conan-obrien-to-host-2025-oscars-academy-awards",
            "urlToImage": "https://image-cdn.hypb.st/https%3A%2F%2Fhypebeast.com%2Fimage%2F2024%2F11%2F15%2Ftw-conan-obrien-to-host-2025-oscars-academy-awards.jpg?w=1080&cbr=1&q=90&fit=max",
            "publishedAt": "2024-11-16T08:56:51Z",
            "content": "The Academy of Motion Picture Arts and Sciences has named Conan O\u2019Brien as the host of the 97th Academy Awards.\r\nThe comedian, host and writer is set to take over hosting duties from Jimmy Kimmel, wh\u2026 [+896 chars]"
        },
        {
            "source": {
                "id": null,
                "name": "[Removed]"
            },
            "author": null,
            "title": "[Removed]",
            "description": "[Removed]",
            "url": "https://removed.com",
            "urlToImage": null,
            "publishedAt": "2024-11-20T11:00:55Z",
            "content": "[Removed]"
        },
        {
            "source": {
                "id": null,
                "name": "Deadline"
            },
            "author": "Antonia Blyth",
            "title": "\u2018Anora\u2019s Mikey Madison On Learning Russian And Portraying Sex Work Respectfully: \u201cThat Was The Ultimate Goal\u201d",
            "description": "At the heart of Sean Baker\u2019s film Anora is Mikey Madison. Having seen her work in Once Upon a Time in Hollywood and Scream, Baker cast her as Ani, a young woman working as a dancer in a New York strip joint and living in Brooklyn\u2019s Brighton Beach neighborhood\u2026",
            "url": "http://deadline.com/2024/11/anora-mikey-madison-stunts-improv-sex-worker-respectfully-speaking-russian-interview-1236173297/",
            "urlToImage": "https://deadline.com/wp-content/uploads/2024/11/Anora-hires-copy.jpg?w=1024",
            "publishedAt": "2024-11-15T19:57:08Z",
            "content": "At the heart of Sean Baker\u2019s film Anora is Mikey Madison. Having seen her work in Once Upon a Time in Hollywood and Scream, Baker cast her as Ani, a young woman working as a dancer in a New York stri\u2026 [+10110 chars]"
        },
        {
            "source": {
                "id": null,
                "name": "Subtraction.com"
            },
            "author": "Khoi",
            "title": "Movies Watched, October 2024",
            "description": "After three home runs I expected \u201cAnora,\u201d Sean Baker\u2019s newest movie, to leave the ballpark, especially after it won the Palme d\u2019Or at Cannes. But it\u2019s just a triple. I don\u2019t know why ba\u2026",
            "url": "https://www.subtraction.com/2024/11/17/movies-watched-october-2024/",
            "urlToImage": "http://www.subtraction.com/wp-content/uploads/2024/11/2024-11-17-anora.jpg",
            "publishedAt": "2024-11-18T02:17:46Z",
            "content": "After three home runs I expected \u201cAnora,\u201d Sean Bakers newest movie, to leave the ballpark, especially after it won the Palme dOr at Cannes. But its just a triple. I dont know why baseball seems like \u2026 [+4847 chars]"
        },
        {
            "source": {
                "id": null,
                "name": "Deadline"
            },
            "author": "Patrick Hipes",
            "title": "Deadline Launches The Contenders Film: Los Angeles Streaming Site",
            "description": "Deadline on Monday launched the streaming site for Contenders Film: Los Angeles, its annual all-say awards-season movie showcase that took place November 16 at the DGA Theater in Hollywood. Click here to launch the streaming site. This year\u2019s lineup featured \u2026",
            "url": "http://deadline.com/2024/11/2024-contenders-film-los-angeles-streaming-site-launches-1236178984/",
            "urlToImage": "https://deadline.com/wp-content/uploads/2024/11/Deadline-Contenders-Film-Los-Angeles-2024.jpg?w=1000",
            "publishedAt": "2024-11-18T20:55:59Z",
            "content": "Deadline on Monday launched the streaming site for Contenders Film: Los Angeles, its annual all-say awards-season movie showcase that took place November 16 at the DGA Theater in Hollywood.\r\nThis yea\u2026 [+1467 chars]"
        },
        {
            "source": {
                "id": null,
                "name": "IndieWire"
            },
            "author": "Anne Thompson",
            "title": "\u2018A Complete Unknown\u2019 Is Heading for Oscars Glory \u2014 Especially for Star Timoth\u00e9e Chalamet",
            "description": "'A Complete Unknown' has finally screened. What are the Oscar chances for James Mangold's Bob Dylan movie, starring Timoth\u00e9e Chalamet?",
            "url": "https://www.indiewire.com/awards/consider-this/a-complete-unknown-oscars-predictions-timothee-chalamet-1235066680/",
            "urlToImage": "https://www.indiewire.com/wp-content/uploads/2024/07/ACompleteUnknown_Trailer1_153_Domestic_3840x2160_2398_Stereo_ProRes422HQ_nwe_20240718.00_01_24_14.Still005.webp?w=650",
            "publishedAt": "2024-11-21T21:22:50Z",
            "content": "Fair warning: your mileage may vary, depending on your relationship to the music of Bob Dylan. James Mangold\u2018s long-gestating \u201cA Complete Unknown\u201d leans heavily on Dylan\u2019s early music and has the pow\u2026 [+2482 chars]"
        },
        {
            "source": {
                "id": null,
                "name": "IndieWire"
            },
            "author": "Tom Brueggemann",
            "title": "How Netflix Put the Hurt on The Rock with $34 Million for Amazon MGM\u2019s \u2018Red One\u2019",
            "description": "In happier news: Filipino romance \"Happy, Love, Again\" scored a nearly $10,000 per-theater average in 248 theaters.",
            "url": "https://www.indiewire.com/news/box-office/how-netflix-hurt-the-rock-amazon-mgm-red-one-1235066617/",
            "urlToImage": "https://www.indiewire.com/wp-content/uploads/2024/11/MCDREON_ZU003.jpg?w=650",
            "publishedAt": "2024-11-17T19:02:39Z",
            "content": "As if theaters don\u2019t already have enough gripes about Netflix, a live event that attracted 60 million households worldwide on a Friday night wasn\u2019t going to make them feel better. Friday night\u2019s Loga\u2026 [+6854 chars]"
        },
        {
            "source": {
                "id": null,
                "name": "Deadline"
            },
            "author": "Patrick Hipes",
            "title": "Deadline\u2019s Contenders Film: Los Angeles Kicks Off Today With 21 Movies In The Awards-Season Race",
            "description": "Contenders Film: Los Angeles, Deadline\u2019s signature and original Contenders event, kicks off its latest edition this morning at 8:30 a.m. PT at the DGA Theater in Hollywood, giving awards voters the opportunity to experience up close and personal the story of \u2026",
            "url": "http://deadline.com/2024/11/2024-contenders-film-los-angeles-movies-schedule-livestream-1236172812/",
            "urlToImage": "https://deadline.com/wp-content/uploads/2024/11/Deadline-Contenders-Film-Los-Angeles-2024.jpg?w=1000",
            "publishedAt": "2024-11-16T16:00:00Z",
            "content": "Contenders Film: Los Angeles, Deadline\u2019s signature and original Contenders event, kicks off its latest edition this morning at 8:30 a.m. PT at the DGA Theater in Hollywood, giving awards voters the o\u2026 [+5163 chars]"
        },
        {
            "source": {
                "id": null,
                "name": "Deadline"
            },
            "author": "jillg366",
            "title": "\u2018Hello, Love, Again\u2019 Sets Opening Record For Filipino Film, Marketing To Vibrant Audience \u201cExhibitors May Have Underestimated\u201d \u2014 Specialty Box Office",
            "description": "Hello, Love, Again, the widest domestic release for a Filipino film, now holds a record for the highest opening weekend for the same with $2.4 million and a no. 8 spot. Jesse Eisenberg\u2019s A Real Pain crossed $3 million at the box office following its expansion\u2026",
            "url": "http://deadline.com/2024/11/indie-film-box-office-hello-love-again-sets-filipino-opening-record-1236179643/",
            "urlToImage": "https://deadline.com/wp-content/uploads/2024/11/image001_e8ad4f.jpg?w=1024",
            "publishedAt": "2024-11-17T18:05:46Z",
            "content": "Hello, Love, Again, the widest domestic release for a Filipino film, now holds a record for the highest opening weekend for the same with $2.4 million and a no. 8 spot.\r\nJesse Eisenberg\u2019s A Real Pain\u2026 [+3212 chars]"
        },
        {
            "source": {
                "id": null,
                "name": "tomandlorenzo.com"
            },
            "author": "Lorenzo Marquez",
            "title": "Style File: ANORA Star Mikey Madison in Mugler and Prada",
            "description": "Anora star Mikey Madison is taking this highly buzzy moment in her career to work two essential looks any rising young movie actress must consider (even if only to reject them): hottie and prestige thespian. \u00a0 IN MUGLER ON JIMMY KIMMEL LIVE! That\u2019s a lot of b\u2026",
            "url": "https://tomandlorenzo.com/2024/11/style-file-anora-star-mikey-madison-in-mugler-and-prada/",
            "urlToImage": "https://tomandlorenzo.com/wp-content/uploads/2024/11/Mikey-Madison-ANORA-Governors-Awards-2024-Jimmy-Kimmel-Fashion-Prada-Mugler-Tom-Lorenzo-Site-0.jpg",
            "publishedAt": "2024-11-18T19:30:44Z",
            "content": "Pin\r\nAnora star Mikey Madison is taking this highly buzzy moment in her career to work two essential looks any rising young movie actress must consider (even if only to reject them): hottie and prest\u2026 [+1451 chars]"
        },
        {
            "source": {
                "id": null,
                "name": "Deadline"
            },
            "author": "Patrick Hipes",
            "title": "Jack Huston And Michael C. Pitt Staged Real Fight At End Of \u2018Day Of The Fight\u2019 \u2013 Contenders Los Angeles",
            "description": "Like its title promises, Day of the Fight climaxes in a boxing match. Star Michael C. Pitt revealed that it was his idea to have a real fight during the production. Writer-director Jack Huston, making his directorial debut, heartily agreed. \u201cI had said to Jac\u2026",
            "url": "http://deadline.com/2024/11/day-of-the-fight-jack-huston-michael-pitt-nicolette-robinson-1236179242/",
            "urlToImage": "https://deadline.com/wp-content/uploads/2024/11/Day-Of-The-Fight-Contenders-LA.jpg?w=1024",
            "publishedAt": "2024-11-16T23:18:11Z",
            "content": "Like its title promises, Day of the Fight climaxes in a boxing match. Star Michael C. Pitt revealed that it was his idea to have a real fight during the production. Writer-director Jack Huston, makin\u2026 [+3277 chars]"
        },
        {
            "source": {
                "id": null,
                "name": "TVLine"
            },
            "author": "Claire Franken",
            "title": "SNL Video: Charli XCX Spoofs Adele, Troye Sivan in Wicked Auditions Sketch \u2014 See More Celebrity Impressions",
            "description": "Wicked has changed Saturday Night Live for good. This weekend\u2019s episode included a sketch claiming to show never-before-seen screen tests for Elphaba and Glinda in the upcoming Wicked film, before Ariana Grande and Cynthia Erivo were chosen for the roles. The\u2026",
            "url": "https://tvline.com/recaps/snl-wicked-auditions-video-1235378443/",
            "urlToImage": "https://tvline.com/wp-content/uploads/2024/11/wicked-auditions-snl.jpg?w=650",
            "publishedAt": "2024-11-17T14:07:30Z",
            "content": "Wicked has changed Saturday Night Live for good. \r\nThis weekend\u2019s episode included a sketch claiming to show never-before-seen screen tests for Elphaba and Glinda in the upcoming Wicked film, before \u2026 [+1181 chars]"
        },
        {
            "source": {
                "id": null,
                "name": "Vulture"
            },
            "author": "Nate Jones",
            "title": "How Every Oscar Movie Can Be the Anti-Trump Movie",
            "description": "Like it or not, we\u2019re in for yet another awards season operating in the shadow of Donald Trump. Which Oscar campaigns can take advantage of the vibe shift?",
            "url": "http://www.vulture.com/article/how-every-oscars-2025-movie-can-be-the-anti-trump-movie.html",
            "urlToImage": "https://pyxis.nymag.com/v1/imgs/1cc/1b2/d31856bc7cab8d23358f16acac156962f8-4ups-Anti-Trump.1x.rsocial.w1200.jpg",
            "publishedAt": "2024-11-16T13:00:37Z",
            "content": "When did you realize your brain had been permanently broken by the election? My moment came last weekend, when I saw Robert Eggerss Nosferatu and couldnt stop thinking of it as the story of local bus\u2026 [+6309 chars]"
        },
        {
            "source": {
                "id": null,
                "name": "Vulture"
            },
            "author": "Roxana Hadadi",
            "title": "We Asked Anora\u2019s Yura Borisov About That Final Scene Inside the Car",
            "description": "Anora\u2019s breakout heartthrob Yura Borisov tells us he approached the ending like \u201cevery second is a new second\u201d for Igor and Ani.",
            "url": "http://www.vulture.com/article/anoras-yura-borisov-on-that-final-scene-inside-the-car.html",
            "urlToImage": "https://pyxis.nymag.com/v1/imgs/9bc/c79/756b6cc9048622b627677300f4b3e5fbae-yura-igor.1x.rsocial.w1200.jpg",
            "publishedAt": "2024-11-15T15:31:32Z",
            "content": "Spoilers follow for the film Anora.\u00a0\r\nFor the second half of Anora, were watching Mikey Madisons abandoned, abused, and determined-to-endure dancer and sex worker through not just our own eyes, but t\u2026 [+10212 chars]"
        },
        {
            "source": {
                "id": null,
                "name": "Thedailymash.co.uk"
            },
            "author": "The Daily Mash",
            "title": "Spray foam insulation \u2018fun to do\u2019, installers explain",
            "description": "",
            "url": "https://www.thedailymash.co.uk/news/society/spray-foam-insulation-fun-to-do-installers-explain-20241118252616",
            "urlToImage": "https://cdn.thedailymash.co.uk/wp-content/uploads/20241118180121/spray-foam-insulation-2000x1124-3.jpg",
            "publishedAt": "2024-11-18T18:02:05Z",
            "content": "HOLLYWOOD has stubbornly continued to make films even though it peaked 25 years ago. None of these recent releases can compare to a rewatch of a 1999 cyberpunk classic:\u00a0\r\nThe Wild Robot (2024)\r\nDeadl\u2026 [+2117 chars]"
        },
        {
            "source": {
                "id": null,
                "name": "Thedailymash.co.uk"
            },
            "author": "The Daily Mash",
            "title": "Spray foam insulation \u2018fun to do\u2019, installers explain",
            "description": "",
            "url": "https://www.thedailymash.co.uk/news/society/spray-foam-insulation-fun-to-do-installers-explain-20241118252616",
            "urlToImage": "https://cdn.thedailymash.co.uk/wp-content/uploads/20241118180121/spray-foam-insulation-2000x1124-3.jpg",
            "publishedAt": "2024-11-18T18:02:05Z",
            "content": "HOLLYWOOD has stubbornly continued to make films even though it peaked 25 years ago. None of these recent releases can compare to a rewatch of a 1999 cyberpunk classic:\u00a0\r\nThe Wild Robot (2024)\r\nDeadl\u2026 [+2117 chars]"
        },
        {
            "source": {
                "id": null,
                "name": "[Removed]"
            },
            "author": null,
            "title": "[Removed]",
            "description": "[Removed]",
            "url": "https://removed.com",
            "urlToImage": null,
            "publishedAt": "2024-11-17T16:55:33Z",
            "content": "[Removed]"
        },
        {
            "source": {
                "id": null,
                "name": "IndieWire"
            },
            "author": "Anne Thompson",
            "title": "Awards Season Is Already in Full Swing \u2014 A Starry, Teary Academy Governors Awards Is Just the Start",
            "description": "On the scene at the annual event, where the late Quincy Jones, filmmaker Richard Curtis, casting director Juliet Taylor, and \"James Bond\" producers Barbara Broccoli and Michael G. Wilson were honored.",
            "url": "https://www.indiewire.com/awards/industry/2024-academy-governors-awards-tribute-quincy-jones-on-the-scene-1235066763/",
            "urlToImage": "https://www.indiewire.com/wp-content/uploads/2024/11/GettyImages-2184757772.jpg?w=650",
            "publishedAt": "2024-11-18T17:35:00Z",
            "content": "The 15th annual Academy Governors Awards on Sunday night brought tears and laughs to the Ray Dolby Ballroom in Hollywood, as usual packed with Oscar hopefuls and AMPAS voters as the awards season get\u2026 [+11279 chars]"
        },
        {
            "source": {
                "id": null,
                "name": "Audioboom.com"
            },
            "author": "The Filmcast, The Filmcast",
            "title": "After Dark: Anora",
            "description": "In this episode, Dave, Jeff, and Devindra discuss Sean Baker's latest film, Anora.\n\nTo get more bonus episodes like this, become a paid subscriber at patreon.com/filmpodcast",
            "url": "https://audioboom.com/posts/8609548-after-dark-anora",
            "urlToImage": "https://audioboom.com/i/42244132",
            "publishedAt": "2024-11-16T22:21:48Z",
            "content": "Sorry, your browser isn't supported by Audioboom.\r\nWe recommend upgrading to the latest\r\n Chrome,\r\n Firefox,\r\n Safari, or\r\n Edge.\r\nPage load failed\r\nPlease check your internet connection and refresh \u2026 [+115 chars]"
        },
        {
            "source": {
                "id": null,
                "name": "[Removed]"
            },
            "author": null,
            "title": "[Removed]",
            "description": "[Removed]",
            "url": "https://removed.com",
            "urlToImage": null,
            "publishedAt": "2024-11-18T11:00:25Z",
            "content": "[Removed]"
        },
        {
            "source": {
                "id": null,
                "name": "Gofugyourself.com"
            },
            "author": "Heather",
            "title": "Cynthia Erivo and Mikey Madison Lead the Last Batch of Elle Women in Hollywood Covers",
            "description": "With SWINTON and\u00a0 Julianne Moore too.\nThe post Cynthia Erivo and Mikey Madison Lead the Last Batch of Elle Women in Hollywood Covers first appeared on Go Fug Yourself.",
            "url": "https://www.gofugyourself.com/cynthia-erivo-and-mikey-madison-lead-the-last-batch-of-elle-women-in-hollywood-covers-11-2024",
            "urlToImage": "https://static.gofugyourself.com/uploads/2024/11/Elle-WIH-part-2-1731617675.jpg",
            "publishedAt": "2024-11-15T19:17:22Z",
            "content": "Earlier today we covered the other covers, and now we\u2019ll round it out with the Wicked and the SWINTON and the Anora of it all. I didn\u2019t get a chance to read the profiles that came with these covers, \u2026 [+705 chars]"
        },
        {
            "source": {
                "id": null,
                "name": "Deadline"
            },
            "author": "Pete Hammond",
            "title": "Governors Awards Present Honorary Oscars To Juliet Taylor, Quincy Jones, Richard Curtis & Bond Producers In Emotional Kickoff To A Long Season",
            "description": "If you had any doubt that the awards season was in full swing, Sunday night\u2019s 15th Annual Governors Awards ceremony answered it. If you are, or in any way think you might have a shot at an Oscar nomination this year, and were in Los Angeles, it is most likely\u2026",
            "url": "http://deadline.com/2024/11/governors-awards-honorary-oscars-juliet-taylor-quincy-jones-richard-curtis-james-bond-producers-1236180346/",
            "urlToImage": "https://deadline.com/wp-content/uploads/2024/11/2184757778.webp?w=1024",
            "publishedAt": "2024-11-18T20:10:11Z",
            "content": "If you had any doubt that the awards season was in full swing, Sunday night\u2019s 15th Annual Governors Awards ceremony answered it. \r\nIf you are, or in any way think you might have a shot at an Oscar no\u2026 [+10268 chars]"
        },
        {
            "source": {
                "id": null,
                "name": "tomandlorenzo.com"
            },
            "author": "Lorenzo Marquez",
            "title": "ELLE\u2019s 2024 Women in Hollywood Issue \u2013 Part One",
            "description": "Danielle Deadwyler History Is Speaking Through Danielle Deadwyler The\u00a0Piano Lesson\u00a0star is highlighting Black stories through her films. On her upcoming role in\u00a0The Piano Lesson,\u00a0which will hit Netflix on November 22, Deadwyler plays Berniece, a mother trying\u2026",
            "url": "https://tomandlorenzo.com/2024/11/elles-2024-women-in-hollywood-issue-part-one/",
            "urlToImage": "https://tomandlorenzo.com/wp-content/uploads/2024/11/ELLE-2024-Women-Hollywood-Issue-Danielle-Deadwyler-Selena-Gomez-Zoe-Saldana-Karla-Sofia-Gascon-Mikey-Madison-TLO-0.jpg",
            "publishedAt": "2024-11-15T17:00:22Z",
            "content": "Posted on November 15, 2024\r\nDanielle Deadwyler\r\nPin\r\nPin\r\nHistory Is Speaking Through Danielle Deadwyler\r\nThe\u00a0Piano Lesson\u00a0star is highlighting Black stories through her films.\r\nOn her upcoming role\u2026 [+9148 chars]"
        },
        {
            "source": {
                "id": null,
                "name": "Celebitchy.com"
            },
            "author": "Kaiser",
            "title": "Jennifer Lawrence wore Bottega Veneta to the Governors Awards: not bad?",
            "description": "Embed from Getty Images I\u2019m sorry to do a big photo dump from Getty, but the Academy really limited the photo agencies\u2019 access to the Governors Awards red carpet. Angelina Jolie bringing her 16-year-old son Knox as her date was maybe the biggest news from the\u2026",
            "url": "https://www.celebitchy.com/898755/jennifer_lawrence_wore_bottega_veneta_to_the_governors_awards_not_bad/",
            "urlToImage": null,
            "publishedAt": "2024-11-18T15:20:39Z",
            "content": "Embed from Getty Images\r\nIm sorry to do a big photo dump from Getty, but the Academy really limited the photo agencies access to the Governors Awards red carpet. Angelina Jolie bringing her 16-year-o\u2026 [+1372 chars]"
        },
        {
            "source": {
                "id": null,
                "name": "Newser"
            },
            "author": "Bob Cronin",
            "title": "Audiences, Studios Seem to Await Wicked, Gladiator II",
            "description": "Moviegoers were not yet feeling the holiday spirit this weekend, or at least not the cheer Red One was offering. The big budget, star-driven action comedy with Dwayne Johnson and Chris Evans sold $34.1 million in tickets in its first weekend in theaters, acco\u2026",
            "url": "https://www.newser.com/story/359633/red-one-tops-weekend-before-wicked-gladiator-ii.html",
            "urlToImage": "https://img2-azrcdn.newser.com/image/1573197-12-20241117124500.jpeg",
            "publishedAt": "2024-11-17T18:15:00Z",
            "content": "Moviegoers were not yet feeling the holiday spirit this weekend, or at least not the cheer Red One was offering. The big budget, star-driven action comedy with Dwayne Johnson and Chris Evans sold $34\u2026 [+1558 chars]"
        },
        {
            "source": {
                "id": null,
                "name": "Boston Herald"
            },
            "author": "Tribune News Service",
            "title": "Oscars 2025: The pickings aren\u2019t slim, provided you take the time to look",
            "description": "It's not even Thanksgiving. Everything is in the mix! Or should be. Even a black-and-white, near-silent slapstick comedy about a 19th-century trapper battling beavers.",
            "url": "https://www.bostonherald.com/2024/11/18/oscars-2025-pickings/",
            "urlToImage": "https://www.bostonherald.com/wp-content/uploads/2024/11/ENTER-MOVIE-OSCARS-CONTENDERS-1-MCT.jpg?w=1024&h=583",
            "publishedAt": "2024-11-18T21:24:54Z",
            "content": "Glenn Whipp | (TNS) Los Angeles Times\r\nLOS ANGELES \u2014 \u201cGladiator II,\u201d the enjoyably dumb sequel to the brawny Ridley Scott epic that won the best picture Oscar nearly a quarter-century ago, has just f\u2026 [+6328 chars]"
        },
        {
            "source": {
                "id": null,
                "name": "Theplaylist.net"
            },
            "author": "Gregory Ellwood",
            "title": "\u2018A Complete Unknown\u2019: Timothee Chalamet & Monica Barbaro Strike An Oscars Chord",
            "description": "Eight years ago, less than two weeks after a shock election that saw he who will not be named on their way to the White House, 20th Century Fox held a screening of \u201cHidden Figures\u201d on the Fox lot. The movie had been considered a borderline Best Picture conten\u2026",
            "url": "https://theplaylist.net/a-complete-unknown-timothee-chalamet-monica-barbaro-oscars-20241121/",
            "urlToImage": "https://cdn.theplaylist.net/wp-content/uploads/2024/11/20162615/TimotheeChalametACompleteUnknown.jpg",
            "publishedAt": "2024-11-21T17:49:56Z",
            "content": "Eight years ago, less than two weeks after a shock election that saw he who will not be named on their way to the White House, 20th Century Fox held a screening of \u201cHidden Figures\u201d on the Fox lot. Th\u2026 [+5543 chars]"
        },
        {
            "source": {
                "id": null,
                "name": "JoBlo.com"
            },
            "author": "Chris Bumbray",
            "title": "Weekend Box Office: Red One has an underwhelming opening",
            "description": "Despite a decent audience rating, Red One proved to be another box office disapointment for The Rock.\nThe post Weekend Box Office: Red One has an underwhelming opening appeared first on JoBlo.",
            "url": "https://www.joblo.com/weekend-box-office-red-one-has-an-underwhelming-opening/",
            "urlToImage": "https://www.joblo.com/wp-content/uploads/2024/04/dwayne-johnson-late-red-one.jpg",
            "publishedAt": "2024-11-17T17:29:46Z",
            "content": "Despite a decent audience rating, Red One proved to be another box office disapointment for The Rock.\r\nIs Dwayne Johnson still as big of a star as he seems to think he is? Thats the question that wil\u2026 [+3214 chars]"
        },
        {
            "source": {
                "id": null,
                "name": "CinemaBlend"
            },
            "author": "Eric Eisenberg",
            "title": "Red One Is The New Number One Movie At The Box Office, But It Has A Rough Road Ahead Of It",
            "description": "Not the big comeback Dwayne Johnson was hoping for.",
            "url": "https://www.cinemablend.com/movies/box-office/red-one-new-number-one-movie-box-office-but-rough-road-ahead-",
            "urlToImage": "https://cdn.mos.cms.futurecdn.net/mwW6moNkM8E5ZhtWtGxnmf-1200-80.jpg",
            "publishedAt": "2024-11-17T20:26:01Z",
            "content": "November in 2024 can be described as backloaded at the box office. With Kelly Marcel's Venom: The Last Dance hitting theaters in late October and major studios giving it a good amount of runway (argu\u2026 [+6651 chars]"
        },
        {
            "source": {
                "id": null,
                "name": "VOA News"
            },
            "author": "webdesk@voanews.com (Associated Press)",
            "title": "Dwayne Johnson's $200 million-plus Christmas pic opens to $34.1 million",
            "description": "Los Angeles \u2014\u00a0Moviegoers were not exactly feeling the Christmas spirit this weekend, or at least not based on their attendance at \"Red One\" showings.\u00a0\n\n\nThe big budget, star-driven action comedy with Dwayne Johnson and Chris Evans sold $34.1 million in ticket\u2026",
            "url": "https://www.voanews.com/a/dwayne-johnson-s-200-million-plus-christmas-pic-opens-to-34-1-million/7867082.html",
            "urlToImage": "https://gdb.voanews.com/FFE734B2-C95C-47A2-A31F-7AD90864A440.jpg",
            "publishedAt": "2024-11-17T20:15:23Z",
            "content": "Los Angeles \u00a0Moviegoers were not exactly feeling the Christmas spirit this weekend, or at least not based on their attendance at \"Red One\" showings. \r\nThe big budget, star-driven action comedy with D\u2026 [+4906 chars]"
        },
        {
            "source": {
                "id": null,
                "name": "Sky.com"
            },
            "author": "Bethany Minelle, arts and entertainment reporter",
            "title": "And the host of the Oscars is\u2026 Conan O'Brien",
            "description": "Conan O'Brien has been announced as the host of next year's Oscars.",
            "url": "https://news.sky.com/story/and-the-host-of-the-oscars-is-conan-obrien-13254682",
            "urlToImage": "https://e3.365dm.com/24/11/1600x900/skynews-conan-obrien-oscars_6749039.jpg?20241115142920",
            "publishedAt": "2024-11-15T14:22:00Z",
            "content": "Conan O'Brien has been announced as the host of next year's Oscars.\r\nIt's the Emmy Award-winning comedian's first time heading up the ceremony, which is Hollywood's most high-profile showbiz event.\r\n\u2026 [+2683 chars]"
        },
        {
            "source": {
                "id": null,
                "name": "Theplaylist.net"
            },
            "author": "Ned Booth",
            "title": "\u2018A Complete Unknown\u2019: First Reactions To James Mangold\u2019s Biopic Single Out Timoth\u00e9e Chalamet\u2019s \u201cTour-De-Force\u201d Performance, Monica Barbaro\u2019s Turn As Joan Baez",
            "description": "\u201cA Complete Unknown,\u201d Oscar contender? That may be the case if the first reactions to James Mangold\u2018s Bob Dylan biopic are to be believed. Critics\u2019 take on the film started trickling out onto social media platforms last night, and the consensus verdict? Mostl\u2026",
            "url": "https://theplaylist.net/a-complete-unknown-first-reactions-james-mangolds-biopic-timothee-chalamet-monica-barbaros-20241121/",
            "urlToImage": "https://cdn.theplaylist.net/wp-content/uploads/2024/11/21090548/A-complete-unknown-timothee-chalamet.jpg",
            "publishedAt": "2024-11-21T14:46:33Z",
            "content": "A Complete Unknown, Oscar contender? That may be the case if the first reactions to James MangoldsBob Dylan biopic are to be believed. Critics take on the film started trickling out onto social media\u2026 [+3625 chars]"
        },
        {
            "source": {
                "id": null,
                "name": "Theplaylist.net"
            },
            "author": "Ned Booth",
            "title": "\u2018A Complete Unknown\u2019: First Reactions To James Mangold\u2019s Biopic Single Out Timoth\u00e9e Chalamet\u2019s \u201cTour-De-Force\u201d Performance, Monica Barbaro\u2019s Turn As Joan Baez",
            "description": "\u201cA Complete Unknown,\u201d Oscar contender? That may be the case if the first reactions to James Mangold\u2018s Bob Dylan biopic are to be believed. Critics\u2019 take on the film started trickling out onto social media platforms last night, and the consensus verdict? Mostl\u2026",
            "url": "https://theplaylist.net/a-complete-unknown-first-reactions-james-mangolds-biopic-timothee-chalamet-monica-barbaros-20241121/",
            "urlToImage": "https://cdn.theplaylist.net/wp-content/uploads/2024/11/21090548/A-complete-unknown-timothee-chalamet.jpg",
            "publishedAt": "2024-11-21T14:46:33Z",
            "content": "A Complete Unknown, Oscar contender? That may be the case if the first reactions to James MangoldsBob Dylan biopic are to be believed. Critics take on the film started trickling out onto social media\u2026 [+3625 chars]"
        },
        {
            "source": {
                "id": null,
                "name": "GamesRadar+"
            },
            "author": "Amy West",
            "title": "From Deadpool and Wolverine to Dune: Part Two, all 10 of the highest-grossing movies of 2024 are sequels \u2013 and it's the first time that's happened in at least 50 years",
            "description": "Wizard of Oz prequel Wicked could wind up threatening the ranking, though",
            "url": "https://www.gamesradar.com/entertainment/movies/from-deadpool-and-wolverine-to-dune-part-two-all-10-of-the-highest-grossing-movies-of-2024-are-sequels-and-its-the-first-time-thats-happened-in-at-least-50-years/",
            "urlToImage": "https://cdn.mos.cms.futurecdn.net/ZjErDfVcENpfSVmBhxDfJX-1200-80.jpg",
            "publishedAt": "2024-11-21T19:03:08Z",
            "content": "All ten of the highest-grossing movies of 2024 are sequels, with Inside Out 2, Deadpool and Wolverine, and Despicable Me 4 taking up the top 3 spots. It marks the first time in 50 years that the enti\u2026 [+4903 chars]"
        },
        {
            "source": {
                "id": null,
                "name": "IndieWire"
            },
            "author": "Chris O'Falt",
            "title": "Inside the \u2018Anora\u2019 House: The Story Behind the Year\u2019s Most Essential Movie Location",
            "description": "Sean Baker and production designer Stephen Phelps on the glass mansion overlooking Mill Basin, Brooklyn that became the year's best movie location.",
            "url": "https://www.indiewire.com/features/interviews/anora-house-behind-the-scenes-best-movie-location-1235066269/",
            "urlToImage": "https://www.indiewire.com/wp-content/uploads/2024/11/Anora-House.jpeg?w=650",
            "publishedAt": "2024-11-15T19:30:00Z",
            "content": "The first hour of \u201cAnora\u201d is designed to feel like a Cinderella story. Ani (Mikey Madison), a Brooklyn sex worker, gets swept up into the whirlwind lifestyle and absurd wealth of Ivan (Mark Eydelshte\u2026 [+9540 chars]"
        },
        {
            "source": {
                "id": null,
                "name": "Pajiba.com"
            },
            "author": "Kayleigh Donaldson",
            "title": "Kate Winslet is Getting Busy With Her One-Woman Oscar Campaign",
            "description": "That's right kids, it's that time of year yet again: awards season. Technically, the hunt for Oscar glory is an endless battle with people in the film industry working year-round to make it happen, but the real action starts hotting...\nRead more...",
            "url": "https://www.pajiba.com/celebrities_are_better_than_you/kate-winslet-is-getting-busy-with-her-onewoman-oscar-campaign-for-lee.php",
            "urlToImage": "https://www.pajiba.com/assets_c/2024/11/Kate%20Winslet%20Leo%20diCaprio%20Getty%201-thumb-700xauto-266769.jpg",
            "publishedAt": "2024-11-21T20:00:00Z",
            "content": "That\u2019s right kids, it\u2019s that time of year yet again: awards season. Technically, the hunt for Oscar glory is an endless battle with people in the film industry working year-round to make it happen, b\u2026 [+7500 chars]"
        },
        {
            "source": {
                "id": "abc-news",
                "name": "ABC News"
            },
            "author": "LINDSEY BAHR AP film writer",
            "title": "Dwayne Johnson\u2019s $200 million+ Christmas pic opens to $34.1 million",
            "description": "The big budget, star-driven action comedy \u201cRed One\u201d has topped the North American box office charts",
            "url": "https://abcnews.go.com/Entertainment/wireStory/dwayne-johnsons-200-million-christmas-pic-opens-341-115946762",
            "urlToImage": "https://i.abcnewsfe.com/a/1c5aed6d-82b6-4125-8580-18b231ca0cd6/wirestory_154e3e132c5993ac25cfcaf39f4b4815_16x9.jpg?w=1600",
            "publishedAt": "2024-11-17T17:18:24Z",
            "content": "LOS ANGELES -- Moviegoers were not exactly feeling the Christmas spirit this weekend, or at least what Red One was offering. The big budget, star-driven action comedy with Dwayne Johnson and Chris Ev\u2026 [+3448 chars]"
        },
        {
            "source": {
                "id": null,
                "name": "[Removed]"
            },
            "author": null,
            "title": "[Removed]",
            "description": "[Removed]",
            "url": "https://removed.com",
            "urlToImage": null,
            "publishedAt": "2024-11-21T11:00:04Z",
            "content": "[Removed]"
        },
        {
            "source": {
                "id": null,
                "name": "ETF Daily News"
            },
            "author": "MarketBeat News",
            "title": "Assetmark Inc. Boosts Stock Holdings in Natera, Inc. (NASDAQ:NTRA)",
            "description": "Assetmark Inc. increased its position in shares of Natera, Inc. (NASDAQ:NTRA \u2013 Free Report) by 2.1% in the 3rd quarter, according to its most recent disclosure with the Securities & Exchange Commission. The institutional investor owned 7,353 shares of the med\u2026",
            "url": "https://www.etfdailynews.com/2024/11/16/assetmark-inc-boosts-stock-holdings-in-natera-inc-nasdaqntra/",
            "urlToImage": "https://www.americanbankingnews.com/wp-content/timthumb/timthumb.php?src=https://www.marketbeat.com/logos/natera-inc-logo-1200x675.jpg?v=20221117161649&w=240&h=240&zc=2",
            "publishedAt": "2024-11-16T08:34:59Z",
            "content": "Assetmark Inc. increased its position in shares of Natera, Inc. (NASDAQ:NTRA \u2013 Free Report) by 2.1% in the 3rd quarter, according to its most recent disclosure with the Securities &amp; Exchange Comm\u2026 [+6096 chars]"
        },
        {
            "source": {
                "id": null,
                "name": "[Removed]"
            },
            "author": null,
            "title": "[Removed]",
            "description": "[Removed]",
            "url": "https://removed.com",
            "urlToImage": null,
            "publishedAt": "2024-11-15T14:32:15Z",
            "content": "[Removed]"
        },
        {
            "source": {
                "id": null,
                "name": "WWD"
            },
            "author": "Marissagmuller",
            "title": "Red Fall Looks Reign at Deadline\u2019s 2024 Contenders Film: Los\u00a0Angeles",
            "description": "Lupita Nyong'o, Saoirse Ronan, Ryan Destiny, and more wore red fall looks at Deadline\u2019s 2024 Contenders: Photos.",
            "url": "http://wwd.com/pop-culture/celebrity-news/red-fall-trend-red-carpet-deadline-contenders-1236725194/",
            "urlToImage": "https://wwd.com/wp-content/uploads/2024/11/red-fall-trend-red-carpet.jpg?w=1000&h=563&crop=1",
            "publishedAt": "2024-11-17T22:52:03Z",
            "content": "Yesterday there was a common theme on the red carpet at Deadline\u2019s 2024 Contenders Film: Los Angeles: red looks for fall. When celebrities walked the red carpet, a handful did so in one of the season\u2026 [+1771 chars]"
        },
        {
            "source": {
                "id": null,
                "name": "WWD"
            },
            "author": "Julia Teti",
            "title": "Jennifer Lawrence Channels Dark Vintage Glamour in Christian Lacroix Dress Accentuating Her Baby Bump at \u2018Bread and Roses\u2019\u00a0Premiere",
            "description": "Jennifer Lawrence gave dark glamour a vintage twist in Christian Lacroix dress accentuating her baby bump at the 'Bread & Roses' premiere in L.A.",
            "url": "http://wwd.com/pop-culture/celebrity-news/jennifer-lawrence-christian-lacroix-bread-roses-premiere-1236723477/",
            "urlToImage": "https://wwd.com/wp-content/uploads/2024/11/jennifer-lawrence-bread-roses-premiere-fi.jpg?w=1000&h=563&crop=1",
            "publishedAt": "2024-11-15T18:56:39Z",
            "content": "Jennifer Lawrence took cues from retro runway fashion for her latest red carpet look, embracing the dark glamour trend at the premiere of the documentary \u201cBread &amp; Roses,\u201d which she coproduced wit\u2026 [+1566 chars]"
        },
        {
            "source": {
                "id": null,
                "name": "Cosmopolitan.com"
            },
            "author": "Courtney Young",
            "title": "It\u2019s Time to Revisit \u2018Gladiator\u2019 Before the Next Installment Hits Theaters",
            "description": "How to watch the original film\u00a0before watching 'Gladiator II,' starring Paul Mescal, Pedro Pascal, and Denzel Washington.",
            "url": "https://www.cosmopolitan.com/entertainment/movies/a62940359/what-to-watch-before-gladiator-2/",
            "urlToImage": "https://hips.hearstapps.com/hmg-prod/images/main1-1-673b80b2f1bf2.jpg?crop=1xw:0.8880994671403197xh;center,top&resize=1200:*",
            "publishedAt": "2024-11-21T15:00:00Z",
            "content": "A darling of our forthcoming awards season is nearly here, and were not talking about Wicked. After a year of anticipation and a thrilling press tour, Gladiator II lands in theaters this month, strai\u2026 [+2214 chars]"
        },
        {
            "source": {
                "id": null,
                "name": "WWD"
            },
            "author": "Hikmat Mohammed",
            "title": "Club Cin\u00e9 Is Making Film Clubs Sexy\u00a0Again",
            "description": "The film club\u2019s screenings have drawn in the likes of Alexander McQueen\u2019s creative director Se\u00e1n McGirr, English filmmaker Edgar Wright and actors Marisa Abela and Hugh Skinner.",
            "url": "http://wwd.com/business-news/media/club-cine-film-clubs-sexy-again-1236723610/",
            "urlToImage": "https://wwd.com/wp-content/uploads/2024/11/club-cine-x.jpg?w=1000&h=563&crop=1",
            "publishedAt": "2024-11-15T17:19:57Z",
            "content": "LONDON \u2014 Club Cin\u00e9, the by-invitation-only film club founded by casting director Tom Macklin, is expanding its reach and is launching an editorial arm by turning its Instagram page @clubcine.ig into \u2026 [+3734 chars]"
        },
        {
            "source": {
                "id": null,
                "name": "[Removed]"
            },
            "author": null,
            "title": "[Removed]",
            "description": "[Removed]",
            "url": "https://removed.com",
            "urlToImage": null,
            "publishedAt": "2024-11-17T18:43:48Z",
            "content": "[Removed]"
        },
        {
            "source": {
                "id": null,
                "name": "Variety"
            },
            "author": "Todd Gilchrist",
            "title": "From \u2018Anora\u2019 to \u2018Wicked,\u2019 Best Picture Hopefuls Race Toward the Oscars Finish Line",
            "description": "The Academy Awards are still months away but the best picture landscape is already taking shape. Some question marks remain \u2014 for example, both \u201cNosferatu\u201d and the Bob Dylan biopic \u201cA Complete Unknown\u201d have yet to be widely seen. And the staying power of smal\u2026",
            "url": "https://variety.com/2024/film/awards/anora-wicked-best-picture-oscar-hopefuls-2025-1236211517/",
            "urlToImage": "https://variety.com/wp-content/uploads/2024/11/Dune-2-1.jpg?w=1000&h=563&crop=1",
            "publishedAt": "2024-11-15T19:16:48Z",
            "content": "The Academy Awards are still months away but the best picture landscape is already taking shape. Some question marks remain \u2014 for example, both \u201cNosferatu\u201d and the Bob Dylan biopic \u201cA Complete Unknow\u2026 [+7241 chars]"
        },
        {
            "source": {
                "id": null,
                "name": "Variety"
            },
            "author": "Emiliana Betancourt",
            "title": "Selena Gomez, Kieran Culkin and Ariana Grande Among SBIFF 2025 Virtuosos Award Honorees",
            "description": "The Santa Barbara International Film Festival has announced its 2025 Virtuosos Award honorees. This year\u2019s honorees are Kieran Culkin (\u201cA Real Pain\u201d), Selena Gomez (\u201cEmilia P\u00e9rez\u201d), Ariana Grande (\u201cWicked\u201d), Harris Dickinson (\u201cBabygirl\u201d), Karla Sof\u00eda Gasc\u00f3n (\u2026",
            "url": "https://variety.com/2024/awards/festivals/santa-barbara-film-festival-2025-virtuosos-award-honorees-1236213933/",
            "urlToImage": "https://variety.com/wp-content/uploads/2024/11/gomez-culkin-grande.jpg?w=1000&h=563&crop=1",
            "publishedAt": "2024-11-19T18:00:00Z",
            "content": "The Santa Barbara International Film Festival has announced its 2025 Virtuosos Award honorees. \r\nThis year\u2019s honorees are Kieran Culkin (\u201cA Real Pain\u201d), Selena Gomez (\u201cEmilia P\u00e9rez\u201d), Ariana Grande (\u2026 [+1540 chars]"
        },
        {
            "source": {
                "id": null,
                "name": "Variety"
            },
            "author": "Clayton Davis",
            "title": "The Oscar Trump Effect: How the Academy Could Reflect Our Turbulent Times",
            "description": "Do the Oscars care who won the presidency? As the country recovers from the emotional rollercoaster of the 2024 presidential election, Hollywood will be coping with this charged political atmosphere at events throughout awards season. And that could determine\u2026",
            "url": "https://variety.com/2024/film/awards/trump-affect-oscars-wicked-best-picture-1236215903/",
            "urlToImage": "https://variety.com/wp-content/uploads/2024/11/Karla-Sofia-Gascon-Cynthia-Erivo.jpg?w=1000&h=563&crop=1",
            "publishedAt": "2024-11-21T16:15:00Z",
            "content": "Do the Oscars care who won the presidency?\r\nAs the country recovers from the emotional rollercoaster of the 2024 presidential election, Hollywood will be coping with this charged political atmosphere\u2026 [+8093 chars]"
        },
        {
            "source": {
                "id": "breitbart-news",
                "name": "Breitbart News"
            },
            "author": "Breitbart News, Breitbart News",
            "title": "Box Office: Amazon-MGM's $200 Million-Plus Christmas Movie Starring Dwayne Johnson Opens to $34.1 million",
            "description": "LOS ANGELES \u2014 Moviegoers were not exactly feeling the Christmas spirit this weekend, or at least not based on their attendance at \u201cRed One\u201d showings.\nThe post Box Office: Amazon-MGM\u2019s $200 Million-Plus Christmas Movie Starring Dwayne Johnson Opens to $34.1 mi\u2026",
            "url": "https://www.breitbart.com/entertainment/2024/11/18/dwayne-johnsons-200-million-plus-christmas-movie-opens-to-34-1-million/",
            "urlToImage": "https://media.breitbart.com/media/2024/11/189b8fc2-eb44-4903-b956-326fe65d6b8b_8e198b74-640x335.jpg",
            "publishedAt": "2024-11-18T11:45:11Z",
            "content": "LOS ANGELES (AP) Moviegoers were not exactly feeling the Christmas spirit this weekend, or at least not based on their attendance at Red One showings.\r\nThe big budget, star-driven action comedy with \u2026 [+4791 chars]"
        },
        {
            "source": {
                "id": null,
                "name": "TheWrap"
            },
            "author": "Steve Pond",
            "title": "Karla Sofia Gasc\u00f3n, Mikey Madison to Receive Virtuosos Award at Santa Barbara Film Festival",
            "description": "Other honorees will be Selena Gomez, Ariana Grande, Kieran Culkin, Harris Dickinson, Clarence Maclin and John Magaro\nThe post Karla Sofia Gasc\u00f3n, Mikey Madison to Receive Virtuosos Award at Santa Barbara Film Festival appeared first on TheWrap.",
            "url": "https://www.thewrap.com/virtuosos-award-karla-sofia-gascon-mikey-madison-sbff/",
            "urlToImage": "https://www.thewrap.com/wp-content/uploads/2024/11/SBIFF-Virtuosos-Award-honorees.png",
            "publishedAt": "2024-11-19T18:03:14Z",
            "content": "Karla Sof\u00eda Gasc\u00f3n, Selena Gomez, Ariana Grande and Mikey Madison are among the eight actors who will be honored with the Santa Barbara Film Festivals Virtuoso Award, an annual honor that goes to up-\u2026 [+798 chars]"
        },
        {
            "source": {
                "id": null,
                "name": "Variety"
            },
            "author": "Varietybrentlang",
            "title": "Fusion Entertainment Signs Documentary Filmmaker and \u2018The Easy Kind\u2019 Director Katy Chevigny (EXCLUSIVE)",
            "description": "Fusion Entertainment has signed veteran documentary filmmaker Katy Chevigny for management on the heels of the world premiere of her first narrative feature, \u201cThe Easy Kind,\u201d at the Telluride Film Festival. Chevigny has produced or directed over a dozen docum\u2026",
            "url": "https://variety.com/2024/film/news/fusion-entertainment-signs-documentary-filmmaker-easy-kind-director-katy-chevigny-1236211395/",
            "urlToImage": "https://variety.com/wp-content/uploads/2024/11/Katy-Chevigny-Headshot-2024.jpeg?w=1000&h=563&crop=1",
            "publishedAt": "2024-11-15T18:40:55Z",
            "content": "Fusion Entertainment has signed veteran documentary filmmaker Katy Chevigny for management on the heels of the world premiere of her first narrative feature, \u201cThe Easy Kind,\u201d at the Telluride Film Fe\u2026 [+1858 chars]"
        },
        {
            "source": {
                "id": null,
                "name": "Variety"
            },
            "author": "Varietybrentlang",
            "title": "Neon, UFO Select \u2018Miss Juneteenth\u2019 Director Channing Godfrey Peoples for Second Feature Development Residency (EXCLUSIVE)",
            "description": "Neon, the Oscar-winning studio behind \u201cParasite\u201d and \u201cAnatomy of a Fall,\u201d and UFO, a nonprofit organization that supports filmmakers, are launching a new residency program to help artists making their sophomore features. The first participant will be filmmake\u2026",
            "url": "https://variety.com/2024/film/news/neon-ufo-miss-juneteenth-channing-godfrey-peoples-second-feature-development-residency-1236215799/",
            "urlToImage": "https://variety.com/wp-content/uploads/2024/11/Channing-Godfrey-Peoples-.jpg?crop=0px%2C63px%2C1200px%2C675px&resize=1000%2C563",
            "publishedAt": "2024-11-20T19:58:00Z",
            "content": "Neon, the Oscar-winning studio behind \u201cParasite\u201d and \u201cAnatomy of a Fall,\u201d and UFO, a nonprofit organization that supports filmmakers, are launching a new residency program to help artists making thei\u2026 [+2368 chars]"
        },
        {
            "source": {
                "id": null,
                "name": "Variety"
            },
            "author": "Chris Willman",
            "title": "Ojai Playhouse Reopens as State-of-the-Art Coastal Showcase for Oscar Contenders, Revival Films and Live Shows, After 10-Year Closure",
            "description": "The city of Ojai has a long-established reputation as one of California\u2019s most quintessentially laid-back small towns. But residents and frequent visitors who have a love for movies may actually have to work up some adrenaline to keep up with the aggressive f\u2026",
            "url": "https://variety.com/2024/film/news/ojai-playhouse-reopens-california-town-oscar-films-revival-1236211120/",
            "urlToImage": "https://variety.com/wp-content/uploads/2024/11/Ojai-Playhouse-exterior-Credit-Ciro-Coelho_Ojai-Playhouse.jpg.jpg?w=1000&h=563&crop=1",
            "publishedAt": "2024-11-15T18:00:24Z",
            "content": "The city of Ojai has a long-established reputation as one of California\u2019s most quintessentially laid-back small towns. But residents and frequent visitors who have a love for movies may actually have\u2026 [+12281 chars]"
        },
        {
            "source": {
                "id": null,
                "name": "Variety"
            },
            "author": "Marcmalkin",
            "title": "Cameron Diaz Makes Rare Public Appearance and Demi Moore Reunites With \u2018Now and Then\u2019 Co-Stars: Inside Elle Women in Hollywood (PHOTOS)",
            "description": "Cameron Diaz made a rare public appearance Tuesday in Los Angeles to help honor \u201cEmilia P\u00e9rez\u201d stars Zoe Salda\u00f1a, Selena Gomez and Karla Sof\u00eda Gasc\u00f3n at Elle magazine\u2019s Women in Hollywood event. \u201cIt\u2019s really quite incredible to be in this room right now becau\u2026",
            "url": "https://variety.com/gallery/cameron-diaz-rare-public-appearance-demi-moore-now-and-then-elle-women-in-hollywood-photos/",
            "urlToImage": "https://variety.com/wp-content/uploads/2024/11/2185686712-1.jpg?crop=0px%2C0px%2C2558px%2C1440px&resize=1000%2C563",
            "publishedAt": "2024-11-20T23:34:28Z",
            "content": "Cameron Diaz made a rare public appearance Tuesday in Los Angeles to help honor Emilia P\u00e9rez stars Zoe Salda\u00f1a, Selena Gomez and Karla Sof\u00eda Gasc\u00f3n at Elle magazines Women in Hollywood event.\r\nIts re\u2026 [+7077 chars]"
        },
        {
            "source": {
                "id": null,
                "name": "Variety"
            },
            "author": "Clayton Davis",
            "title": "Conan O\u2019Brien to Host 2025 Oscars Ceremony",
            "description": "Emmy-winning comedian, writer, producer and former late-night host Conan O\u2019Brien has been tapped to host the 97th Oscars, the Academy of Motion Picture Arts and Sciences announced Tuesday. This marks O\u2019Brien\u2019s first stint as as host, coming after two consecut\u2026",
            "url": "https://variety.com/2024/film/awards/conan-obrien-oscars-host-2025-1236210975/",
            "urlToImage": "https://variety.com/wp-content/uploads/2024/11/1000020095.jpg?w=1000&h=563&crop=1",
            "publishedAt": "2024-11-15T13:30:00Z",
            "content": "Emmy-winning comedian, writer, producer and former late-night host Conan O\u2019Brien has been tapped to host the 97th Oscars, the Academy of Motion Picture Arts and Sciences announced Tuesday.\r\nThis mark\u2026 [+2828 chars]"
        },
        {
            "source": {
                "id": null,
                "name": "WHIO"
            },
            "author": "Lindsey Bahr",
            "title": "Dwayne Johnson\u2019s $200 million-plus Christmas pic opens to $34.1 million",
            "description": "The big budget, star-driven action comedy \u201cRed One\u201d is topping the North American box office charts",
            "url": "https://www.whio.com/entertainment/dwayne-johnsons-200/GQOWDCU4XJBQBHAB5EMD7W7OMI/",
            "urlToImage": "https://cmg-cmg-tv-10040-prod.cdn.arcpublishing.com/resizer/6-ublLis8geY6qDBU6A9d0U_AcU=/1440x810/filters:format(jpg):quality(70)/cloudfront-us-east-1.images.arcpublishing.com/cmg/3MB2H4XLAMJXLDBAT6VCUAPOQA.jpg",
            "publishedAt": "2024-11-18T02:20:06Z",
            "content": "LOS ANGELES \u2014 (AP) Moviegoers were not exactly feeling the Christmas spirit this weekend, or at least not based on their attendance at \"Red One\" showings.\r\nThe big budget, star-driven action comedy w\u2026 [+4980 chars]"
        },
        {
            "source": {
                "id": null,
                "name": "ksltv.com"
            },
            "author": "Associated Press",
            "title": "Dwayne Johnson\u2019s $200 million-plus Christmas pic, 'Red One,' opens to $34.1 million",
            "description": "The big budget, star-driven action comedy \u201cRed One\u201d is topping the North American box office charts.",
            "url": "https://ksltv.com/707150/dwayne-johnsons-200-million-plus-christmas-pic-red-one-opens-to-34-1-million/",
            "urlToImage": "https://ksltv.com/wp-content/uploads/2024/11/Film_Review_-_Red_One_55789-e1731883123251.jpg",
            "publishedAt": "2024-11-17T23:04:05Z",
            "content": "LOS ANGELES (AP) Moviegoers were not exactly feeling the Christmas spirit this weekend, or at least not based on their attendance at\u00a0Red One\u00a0showings.\r\nThe big budget, star-driven action comedy with \u2026 [+4799 chars]"
        },
        {
            "source": {
                "id": null,
                "name": "Variety"
            },
            "author": "Rebecca Rubin",
            "title": "How \u2018Conclave\u2019 Become One of Awards Season\u2019s Biggest Indie Box Office Hits",
            "description": "After four weeks on the big screen, \u201cConclave\u201d has managed to do something that few other adult-skewing films have achieved in the post-pandemic era: Sell some tickets. Director Edward Berger\u2019s mystery thriller about the politicking and backstabbing behind th\u2026",
            "url": "https://variety.com/2024/film/box-office/conclave-box-office-success-adult-oscar-films-1236210375/",
            "urlToImage": "https://variety.com/wp-content/uploads/2024/10/Conclave-Movie.jpg?w=1000&h=563&crop=1",
            "publishedAt": "2024-11-18T15:24:20Z",
            "content": "After four weeks on the big screen, \u201cConclave\u201d has managed to do something that few other adult-skewing films have achieved in the post-pandemic era: Sell some tickets.\r\nDirector Edward Berger\u2019s myst\u2026 [+5266 chars]"
        },
        {
            "source": {
                "id": null,
                "name": "Variety"
            },
            "author": "Jenelleriley2",
            "title": "SAG Awards\u00a02025 Preview: Breaking Down the Top\u00a0Film and TV Contenders",
            "description": "The 31st Screen Actors Guild Awards will be held on Feb. 23, 2025, with nominations announced Jan. 8. But movies and TV shows are already jockeying for position in the awards race, which are voted on by SAG-AFTRA actors. Variety took a look at some of the tit\u2026",
            "url": "https://variety.com/2024/awards/awards/sag-awards-2025-preview-1236214454/",
            "urlToImage": "https://variety.com/wp-content/uploads/2024/11/wicked-squid-game-split.jpg?w=1000&h=563&crop=1",
            "publishedAt": "2024-11-20T17:05:00Z",
            "content": "The 31st Screen Actors Guild Awards will be held on Feb. 23, 2025, with nominations announced Jan. 8. But movies and TV shows are already jockeying for position in the awards race, which are voted on\u2026 [+7839 chars]"
        },
        {
            "source": {
                "id": null,
                "name": "TheWrap"
            },
            "author": "Steve Pond",
            "title": "Emotional Quincy Jones Tribute Highlights Governors Awards \u2026 But Hugh Grant Calling an Honoree an \u2018A-hole\u201d Was Cool, Too",
            "description": "Jones, Juliet Taylor, Richard Curtis and Michael G. Wilson & Barbara Broccoli receive honorary awards at packed Academy event\nThe post Emotional Quincy Jones Tribute Highlights Governors Awards \u2026 But Hugh Grant Calling an Honoree an \u2018A-hole\u201d Was Cool, Too app\u2026",
            "url": "https://www.thewrap.com/quincy-jones-governors-awards-hugh-grant/",
            "urlToImage": "https://www.thewrap.com/wp-content/uploads/2024/11/Governors-Awards-2024.jpg",
            "publishedAt": "2024-11-18T14:44:15Z",
            "content": "Hugh Grant called an Honorary Oscar winner an ahole, studios spent big money to show off all their awards contenders and a posthumous tribute to Quincy Jones left everybody buzzing at the Academys 15\u2026 [+8613 chars]"
        }
    ]
}